{
  "main": {
    "id": "dd5b784276b3e7fa",
    "type": "split",
    "children": [
      {
        "id": "4990a8a98dccf0d5",
        "type": "tabs",
        "children": [
          {
            "id": "31b273765e96faa2",
            "type": "leaf",
            "state": {
              "type": "markdown",
              "state": {
                "file": "nomenclatures in nice.md",
                "mode": "source",
                "source": false,
                "backlinks": false
              },
              "icon": "lucide-file",
              "title": "nomenclatures in nice"
            }
          },
          {
            "id": "3989e507be750852",
            "type": "leaf",
            "state": {
              "type": "markdown",
              "state": {
                "file": "ckd classification.md",
                "mode": "source",
                "source": false,
                "backlinks": false
              },
              "icon": "lucide-file",
              "title": "ckd classification"
            }
          },
          {
            "id": "a708e8d53962263f",
            "type": "leaf",
            "state": {
              "type": "canvas",
              "state": {
                "file": "flow charts/prostaglandins and leukotrienes.canvas",
                "viewState": {
                  "x": -92.5,
                  "y": 409,
                  "zoom": -0.26317650827575956
                }
              },
              "icon": "lucide-layout-dashboard",
              "title": "prostaglandins and leukotrienes"
            }
          },
          {
            "id": "67ff8593c52c0cd3",
            "type": "leaf",
            "state": {
              "type": "markdown",
              "state": {
                "file": "emollients.md",
                "mode": "source",
                "source": false,
                "backlinks": false
              },
              "icon": "lucide-file",
              "title": "emollients"
            }
          },
          {
            "id": "5235a8de58214c88",
            "type": "leaf",
            "state": {
              "type": "markdown",
              "state": {
                "file": "plaque psoriasis.md",
                "mode": "source",
                "source": false,
                "backlinks": false
              },
              "icon": "lucide-file",
              "title": "plaque psoriasis"
            }
          },
          {
            "id": "d0dcebbdcc52b4d3",
            "type": "leaf",
            "state": {
              "type": "webviewer",
              "state": {
                "url": "https://geekymedics.com/fundoscopy-ophthalmoscopy-osce-guide/#Assess_the_fundus",
                "title": "Fundoscopy (Ophthalmoscopy) - OSCE Guide | Geeky Medics",
                "mode": "webview"
              },
              "icon": "globe-2",
              "title": "Fundoscopy (Ophthalmoscopy) - OSCE Guide | Geeky Medics"
            }
          },
          {
            "id": "30064edbdbbf7fcf",
            "type": "leaf",
            "state": {
              "type": "markdown",
              "state": {
                "file": "steroids in dermatology.md",
                "mode": "source",
                "source": false,
                "backlinks": false
              },
              "icon": "lucide-file",
              "title": "steroids in dermatology"
            }
          },
          {
            "id": "cdfe4e4241b28ae3",
            "type": "leaf",
            "state": {
              "type": "webviewer",
              "state": {
                "url": "https://www.bristol.ac.uk/media-library/sites/primaryhealthcare/documents/eWAP%20v1_0.pdf",
                "title": "eWAP v1_0.pdf",
                "mode": "webview"
              },
              "icon": "globe-2",
              "title": "eWAP v1_0.pdf"
            }
          },
          {
            "id": "dfe9c2ddc7c883ff",
            "type": "leaf",
            "state": {
              "type": "markdown",
              "state": {
                "file": "emollients.md",
                "mode": "source",
                "source": false,
                "backlinks": false
              },
              "icon": "lucide-file",
              "title": "emollients"
            }
          },
          {
            "id": "b0244e90ff75bd73",
            "type": "leaf",
            "state": {
              "type": "markdown",
              "state": {
                "file": "otitis.md",
                "mode": "source",
                "source": false,
                "backlinks": false
              },
              "icon": "lucide-file",
              "title": "otitis"
            }
          }
        ],
        "currentTab": 9
      }
    ],
    "direction": "vertical"
  },
  "left": {
    "id": "5be7ae1656356a94",
    "type": "split",
    "children": [
      {
        "id": "dd6b9f486e1006c5",
        "type": "tabs",
        "dimension": 50,
        "children": [
          {
            "id": "676efa40181a3294",
            "type": "leaf",
            "state": {
              "type": "file-explorer",
              "state": {
                "sortOrder": "alphabetical",
                "autoReveal": false
              },
              "icon": "lucide-folder-closed",
              "title": "Files"
            }
          },
          {
            "id": "e8655fe722644f1f",
            "type": "leaf",
            "state": {
              "type": "search",
              "state": {
                "query": "otitis ex",
                "matchingCase": false,
                "explainSearch": true,
                "collapseAll": true,
                "extraContext": true,
                "sortOrder": "alphabetical"
              },
              "icon": "lucide-search",
              "title": "Search"
            }
          },
          {
            "id": "45c89f1bb0c7f564",
            "type": "leaf",
            "state": {
              "type": "bookmarks",
              "state": {},
              "icon": "lucide-bookmark",
              "title": "Bookmarks"
            }
          },
          {
            "id": "9b8ea1d24095385d",
            "type": "leaf",
            "state": {
              "type": "webviewer-history",
              "state": {},
              "icon": "lucide-clock",
              "title": "Web history"
            }
          }
        ],
        "currentTab": 1
      },
      {
        "id": "cc0aaf324fadf4fd",
        "type": "tabs",
        "dimension": 50,
        "children": [
          {
            "id": "66b70f772136150d",
            "type": "leaf",
            "state": {
              "type": "localgraph",
              "state": {
                "file": "otitis.md",
                "options": {
                  "collapse-filter": true,
                  "search": "",
                  "localJumps": 1,
                  "localBacklinks": true,
                  "localForelinks": true,
                  "localInterlinks": false,
                  "showTags": false,
                  "showAttachments": false,
                  "hideUnresolved": false,
                  "collapse-color-groups": true,
                  "colorGroups": [],
                  "collapse-display": true,
                  "showArrow": false,
                  "textFadeMultiplier": 0,
                  "nodeSizeMultiplier": 1,
                  "lineSizeMultiplier": 1,
                  "collapse-forces": true,
                  "centerStrength": 0.518713248970312,
                  "repelStrength": 10,
                  "linkStrength": 1,
                  "linkDistance": 250,
                  "scale": 1.0534978902533882,
                  "close": true
                }
              },
              "icon": "lucide-git-fork",
              "title": "Graph of otitis"
            }
          }
        ]
      }
    ],
    "direction": "horizontal",
    "width": 397.5044631958008
  },
  "right": {
    "id": "18cd351862e29aca",
    "type": "split",
    "children": [
      {
        "id": "c32654b7ac1c916a",
        "type": "tabs",
        "dimension": 38.095238095238095,
        "children": [
          {
            "id": "76e084a2bc339e0c",
            "type": "leaf",
            "state": {
              "type": "outgoing-link",
              "state": {
                "file": "corticosteroid.md",
                "linksCollapsed": false,
                "unlinkedCollapsed": true
              },
              "icon": "links-going-out",
              "title": "Outgoing links from corticosteroid"
            }
          },
          {
            "id": "4b3abad75a1d0653",
            "type": "leaf",
            "state": {
              "type": "tag",
              "state": {
                "sortOrder": "frequency",
                "useHierarchy": true,
                "showSearch": false,
                "searchQuery": ""
              },
              "icon": "lucide-tags",
              "title": "Tags"
            }
          },
          {
            "id": "91c8e30ab36bd5e3",
            "type": "leaf",
            "state": {
              "type": "outline",
              "state": {
                "file": "corticosteroid.md",
                "followCursor": false,
                "showSearch": false,
                "searchQuery": ""
              },
              "icon": "lucide-list",
              "title": "Outline of corticosteroid"
            }
          },
          {
            "id": "82c94cd72e9e5367",
            "type": "leaf",
            "state": {
              "type": "all-properties",
              "state": {
                "sortOrder": "frequency",
                "showSearch": false,
                "searchQuery": ""
              },
              "icon": "lucide-archive",
              "title": "All properties"
            }
          },
          {
            "id": "d7f371dc268b2234",
            "type": "leaf",
            "state": {
              "type": "git-view",
              "state": {},
              "icon": "git-pull-request",
              "title": "Source Control"
            }
          },
          {
            "id": "f773b2f74c015d2b",
            "type": "leaf",
            "state": {
              "type": "file-properties",
              "state": {
                "file": "corticosteroid.md"
              },
              "icon": "lucide-info",
              "title": "File properties for corticosteroid"
            }
          }
        ],
        "currentTab": 4
      },
      {
        "id": "c9a800b7c85d029b",
        "type": "tabs",
        "dimension": 61.904761904761905,
        "children": [
          {
            "id": "639b2a927a3a9294",
            "type": "leaf",
            "state": {
              "type": "backlink",
              "state": {
                "file": "otitis.md",
                "collapseAll": false,
                "extraContext": false,
                "sortOrder": "alphabetical",
                "showSearch": false,
                "searchQuery": "",
                "backlinkCollapsed": false,
                "unlinkedCollapsed": false
              },
              "icon": "links-coming-in",
              "title": "Backlinks for otitis"
            }
          }
        ]
      }
    ],
    "direction": "horizontal",
    "width": 541.5
  },
  "left-ribbon": {
    "hiddenItems": {
      "bases:Create new base": false,
      "switcher:Open quick switcher": false,
      "canvas:Create new canvas": false,
      "command-palette:Open command palette": false,
      "obsidian-git:Open Git source control": false,
      "obsifetch:obsifetch": false,
      "graph:Open graph view": false
    }
  },
  "active": "b0244e90ff75bd73",
  "lastOpenFiles": [
    "human herpes viruses.md",
    "cold sores.md",
    "school in children with rash.md",
    "emollients.md",
    "desktop.ini",
    "cancer- skin.md",
    "urea.md",
    "eczema.md",
    "steroids in dermatology.md",
    "nappy rash.md",
    "corticosteroid.md",
    "croup.md",
    "plaque psoriasis.md",
    "psoriasis.md",
    "seborrhoeic dermatitis.md",
    "seborrhoeic keratosis.md",
    "atopic diseases.md",
    "vitiligo.md",
    "koebner's phenomenon.md",
    "hypothyroidism.md",
    "retinopathy.md",
    "actinic keratosis.md",
    "loss of vision.md",
    "Vitreous haemorrhage.md",
    "crao.md",
    "ophthalmoscopy.md",
    "platelets.md",
    "flow charts/paeds examination.canvas",
    "flow charts/prostaglandins and leukotrienes.canvas",
    "flow charts/hypertension management.canvas",
    "housekeeping/memorise.base",
    "housekeeping/revise recent changes.base",
    "Clippings",
    "attachments/ng254- suspected-sepsis-managing-and-evaluating-risk-all-settings-pdf-15494830813.pdf",
    "attachments/ng254- evaluating-risk-of-severe-illness-or-death-in-all-settings-children-under-5-pdf-15494513294.pdf",
    "flow charts/h. pylori treatment flowchart.canvas",
    "attachments/universal-pain-assessment-tool-with-wong-baker-facesc2ae-pain-rating-scale.jpg",
    "attachments/anticholinergic burden.png",
    "Untitled",
    "attachments/erectile dysfunction- management guidelines in primary care for adults.pdf",
    "attachments/bronchovesicular-2.mp3",
    "attachments/carhart's notch (otosclerosis).png",
    "attachments/bronchial-sound-2.mp3",
    "attachments/breath sounds.jpg",
    "flow charts/contraception after delivery.canvas",
    "flow charts/haematuria.canvas",
    "flow charts/deep vein thrombosis.canvas",
    "attachments/erythema nodosum.jpg",
    "attachments/erythema multiforme.jpg",
    "attachments/erythema marginatum.jpg",
    "attachments/erythema infectiosum.jpg",
    "attachments/coeliac disease- dermatitis herpetiformis 2.jpg",
    "attachments/erythema gyratum repens.jpg",
    "flow charts/chicken pox treatment flowchart (work in progress).canvas",
    "_chicken Pox treatment flowchart (Work in progress).canvas",
    "Chicken Pox treatment flowchart (Work in progress).canvas"
  ]
}